airflow/__init__.py
airflow/alembic.ini
airflow/configuration.py
airflow/default_login.py
airflow/exceptions.py
airflow/logging_config.py
airflow/plugins_manager.py
airflow/settings.py
airflow/version.py
airflow/_vendor/__init__.py
airflow/_vendor/nvd3/NVD3Chart.py
airflow/_vendor/nvd3/__init__.py
airflow/_vendor/nvd3/cumulativeLineChart.py
airflow/_vendor/nvd3/discreteBarChart.py
airflow/_vendor/nvd3/ipynb.py
airflow/_vendor/nvd3/lineChart.py
airflow/_vendor/nvd3/linePlusBarChart.py
airflow/_vendor/nvd3/lineWithFocusChart.py
airflow/_vendor/nvd3/multiBarChart.py
airflow/_vendor/nvd3/multiBarHorizontalChart.py
airflow/_vendor/nvd3/pieChart.py
airflow/_vendor/nvd3/scatterChart.py
airflow/_vendor/nvd3/stackedAreaChart.py
airflow/_vendor/nvd3/translator.py
airflow/_vendor/slugify/__init__.py
airflow/_vendor/slugify/slugify.py
airflow/api/__init__.py
airflow/api/auth/__init__.py
airflow/api/auth/backend/__init__.py
airflow/api/auth/backend/default.py
airflow/api/auth/backend/deny_all.py
airflow/api/auth/backend/kerberos_auth.py
airflow/api/client/__init__.py
airflow/api/client/api_client.py
airflow/api/client/json_client.py
airflow/api/client/local_client.py
airflow/api/common/__init__.py
airflow/api/common/experimental/__init__.py
airflow/api/common/experimental/delete_dag.py
airflow/api/common/experimental/get_code.py
airflow/api/common/experimental/get_dag_run_state.py
airflow/api/common/experimental/get_dag_runs.py
airflow/api/common/experimental/get_task.py
airflow/api/common/experimental/get_task_instance.py
airflow/api/common/experimental/mark_tasks.py
airflow/api/common/experimental/pool.py
airflow/api/common/experimental/trigger_dag.py
airflow/bin/__init__.py
airflow/bin/airflow
airflow/bin/cli.py
airflow/config_templates/__init__.py
airflow/config_templates/airflow_local_settings.py
airflow/config_templates/default_airflow.cfg
airflow/config_templates/default_celery.py
airflow/config_templates/default_test.cfg
edu_airflow-1.10.5.dist-info/LICENSE
edu_airflow-1.10.5.dist-info/LICENSE-ace.txt
edu_airflow-1.10.5.dist-info/LICENSE-bootstrap-toggle.txt
edu_airflow-1.10.5.dist-info/LICENSE-bootstrap.txt
edu_airflow-1.10.5.dist-info/LICENSE-bootstrap3-typeahead.txt
edu_airflow-1.10.5.dist-info/LICENSE-d3-tip.txt
edu_airflow-1.10.5.dist-info/LICENSE-d3js.txt
edu_airflow-1.10.5.dist-info/LICENSE-dagre-d3.txt
edu_airflow-1.10.5.dist-info/LICENSE-datatables.txt
edu_airflow-1.10.5.dist-info/LICENSE-elasticmock.txt
edu_airflow-1.10.5.dist-info/LICENSE-flask-kerberos.txt
edu_airflow-1.10.5.dist-info/LICENSE-hue.txt
edu_airflow-1.10.5.dist-info/LICENSE-jqclock.txt
edu_airflow-1.10.5.dist-info/LICENSE-jquery.txt
edu_airflow-1.10.5.dist-info/LICENSE-moment.txt
edu_airflow-1.10.5.dist-info/LICENSE-normalize.txt
edu_airflow-1.10.5.dist-info/LICENSE-parallel-coordinates.txt
edu_airflow-1.10.5.dist-info/LICENSE-python-nvd3.txt
edu_airflow-1.10.5.dist-info/LICENSE-python-slugify.txt
edu_airflow-1.10.5.dist-info/LICENSE-scikit-learn.txt
edu_airflow-1.10.5.dist-info/LICENSE-underscorejs.txt
edu_airflow-1.10.5.dist-info/LICENSE-webgl-2d.txt
edu_airflow-1.10.5.dist-info/METADATA
edu_airflow-1.10.5.dist-info/NOTICE
edu_airflow-1.10.5.dist-info/WHEEL
edu_airflow-1.10.5.dist-info/top_level.txt
edu_airflow-1.10.5.dist-info/RECORD
